pspipe_utils/__init__.py
pspipe_utils/_version.py
pspipe_utils/beam_chromaticity.py
pspipe_utils/best_fits.py
pspipe_utils/consistency.py
pspipe_utils/covariance.py
pspipe_utils/external_data.py
pspipe_utils/io.py
pspipe_utils/kspace.py
pspipe_utils/leakage.py
pspipe_utils/log.py
pspipe_utils/misc.py
pspipe_utils/poisson_sources.py
pspipe_utils/pol_angle.py
pspipe_utils/pspipe_list.py
pspipe_utils/simulation.py
pspipe_utils/transfer_function.py
pspipe_utils/data/beams/coadd_pa4_f150_night_beam_tform_jitter_cmb.txt
pspipe_utils/data/beams/coadd_pa4_f150_night_beam_tform_jitter_mono.txt
pspipe_utils/data/beams/coadd_pa4_f220_night_beam_tform_jitter_cmb.txt
pspipe_utils/data/beams/coadd_pa4_f220_night_beam_tform_jitter_mono.txt
pspipe_utils/data/beams/coadd_pa5_f090_night_beam_tform_jitter_cmb.txt
pspipe_utils/data/beams/coadd_pa5_f090_night_beam_tform_jitter_mono.txt
pspipe_utils/data/beams/coadd_pa5_f150_night_beam_tform_jitter_cmb.txt
pspipe_utils/data/beams/coadd_pa5_f150_night_beam_tform_jitter_mono.txt
pspipe_utils/data/beams/coadd_pa6_f090_night_beam_tform_jitter_cmb.txt
pspipe_utils/data/beams/coadd_pa6_f090_night_beam_tform_jitter_mono.txt
pspipe_utils/data/beams/coadd_pa6_f150_night_beam_tform_jitter_cmb.txt
pspipe_utils/data/beams/coadd_pa6_f150_night_beam_tform_jitter_mono.txt
pspipe_utils/data/beams/pa4_f150_gamma_t2b.txt
pspipe_utils/data/beams/pa4_f150_gamma_t2e.txt
pspipe_utils/data/beams/pa4_f220_gamma_t2b.txt
pspipe_utils/data/beams/pa4_f220_gamma_t2e.txt
pspipe_utils/data/beams/pa5_f090_gamma_t2b.txt
pspipe_utils/data/beams/pa5_f090_gamma_t2e.txt
pspipe_utils/data/beams/pa5_f150_gamma_t2b.txt
pspipe_utils/data/beams/pa5_f150_gamma_t2e.txt
pspipe_utils/data/beams/pa6_f090_gamma_t2b.txt
pspipe_utils/data/beams/pa6_f090_gamma_t2e.txt
pspipe_utils/data/beams/pa6_f150_gamma_t2b.txt
pspipe_utils/data/beams/pa6_f150_gamma_t2e.txt
pspipe_utils/data/binaries/binary_dr6_pa4_f150_downgraded.fits
pspipe_utils/data/binaries/binary_dr6_pa4_f220_downgraded.fits
pspipe_utils-1.0.0.dist-info/LICENSE
pspipe_utils-1.0.0.dist-info/METADATA
pspipe_utils-1.0.0.dist-info/WHEEL
pspipe_utils-1.0.0.dist-info/top_level.txt
pspipe_utils-1.0.0.dist-info/RECORD
