Metadata-Version: 2.2
Name: pspipe_utils
Version: 1.0.0
Summary: SO pipeline utilities
Requires-Python: >=3.9
License-File: LICENSE
Requires-Dist: pspy>=1.5.3
Requires-Dist: scikit-learn>=1
Requires-Dist: mflike>=1.0.0
Dynamic: description
Dynamic: description-content-type
Dynamic: requires-dist
Dynamic: requires-python
Dynamic: summary
